smc_monitoring/__init__.py
smc_monitoring/wsocket.py
smc_monitoring/models/__init__.py
smc_monitoring/models/calendar.py
smc_monitoring/models/constants.py
smc_monitoring/models/filters.py
smc_monitoring/models/formats.py
smc_monitoring/models/formatters.py
smc_monitoring/models/query.py
smc_monitoring/models/values.py
smc_monitoring/monitors/__init__.py
smc_monitoring/monitors/alerts.py
smc_monitoring/monitors/blacklist.py
smc_monitoring/monitors/connections.py
smc_monitoring/monitors/logs.py
smc_monitoring/monitors/routes.py
smc_monitoring/monitors/sslvpn.py
smc_monitoring/monitors/users.py
smc_monitoring/monitors/vpns.py
smc_monitoring/pubsub/__init__.py
smc_monitoring/pubsub/subscribers.py
smc_python_monitoring-1.2.0.dist-info/DESCRIPTION.rst
smc_python_monitoring-1.2.0.dist-info/METADATA
smc_python_monitoring-1.2.0.dist-info/RECORD
smc_python_monitoring-1.2.0.dist-info/WHEEL
smc_python_monitoring-1.2.0.dist-info/metadata.json
smc_python_monitoring-1.2.0.dist-info/top_level.txt
tests/__init__.py
tests/constants.py
tests/docker_smc_bootstrap.py
tests/test_filters.py
tests/test_integration.py
tests/test_integration_monitors.py
tests/test_notifications.py
tests/test_queries.py
