Metadata-Version: 2.0
Name: smc-python-monitoring
Version: 1.2.0
Summary: Stonesoft Management Center Monitoring
Home-page: https://github.com/gabstopper/smc-python
Author: David LePage
Author-email: dwlepage70@gmail.com
License: Apache License
Platform: UNKNOWN
Classifier: Development Status :: 5 - Production/Stable
Classifier: Programming Language :: Python
Classifier: Programming Language :: Python :: 2.7
Classifier: Programming Language :: Python :: 3.4
Classifier: Programming Language :: Python :: 3.5
Classifier: Programming Language :: Python :: 3
Classifier: License :: OSI Approved :: Apache Software License
Requires-Dist: smc-python (>=0.6.0)
Requires-Dist: websocket-client (>=0.48.0)
